pubcode/code128.py
pubcode/__init__.py
PubCode-1.1.0.dist-info/top_level.txt
PubCode-1.1.0.dist-info/WHEEL
PubCode-1.1.0.dist-info/metadata.json
PubCode-1.1.0.dist-info/RECORD
PubCode-1.1.0.dist-info/METADATA
PubCode-1.1.0.dist-info/DESCRIPTION.rst
