Metadata-Version: 2.0
Name: PubCode
Version: 1.1.0
Summary: A simple module for creating barcodes.
Home-page: https://github.com/Venti-/pubcode
Author: Ari Koivula
Author-email: ari@koivu.la
License: MIT
Platform: UNKNOWN
Classifier: Development Status :: 4 - Beta
Classifier: Intended Audience :: Developers
Classifier: Topic :: Software Development :: Libraries :: Python Modules
Classifier: Topic :: Multimedia :: Graphics
Classifier: License :: OSI Approved :: MIT License
Classifier: Operating System :: OS Independent
Classifier: Programming Language :: Python :: 2.7
Classifier: Programming Language :: Python :: 3.4
Requires-Dist: future
